setup.py
session_cart/__init__.py
session_cart/cart.py
session_cart/context_processors.py
session_cart/middleware.py
session_cart/settings.py
session_cart/utils.py
session_cart.egg-info/PKG-INFO
session_cart.egg-info/SOURCES.txt
session_cart.egg-info/dependency_links.txt
session_cart.egg-info/not-zip-safe
session_cart.egg-info/top_level.txt