Metadata-Version: 1.0
Name: session-cart
Version: 1.2.0
Summary: A session-stored cart for Django
Home-page: https://github.com/n3storm/session_cart
Author: Curtis Maloney, Grigoriy Bezyuk, Nestor Diaz
Author-email: curtis@tinbrain.net, gbezyuk@gmail.com, nestor@coobleiben.coop
License: UNKNOWN
Keywords: django,cms,e-commerce
Platform: UNKNOWN
Classifier: Environment :: Web Environment
Classifier: Framework :: Django
Classifier: Intended Audience :: Developers
Classifier: License :: OSI Approved :: BSD License
Classifier: Operating System :: OS Independent
Classifier: Programming Language :: Python
Classifier: Topic :: Software Development :: Libraries :: Application Frameworks
Classifier: Topic :: Software Development :: Libraries :: Python Modules
